stac_check/__init__.py
stac_check/api_lint.py
stac_check/cli.py
stac_check/display_messages.py
stac_check/lint.py
stac_check/logo.py
stac_check/stac-check.config.yml
stac_check/utilities.py
stac_check-1.11.1.dist-info/LICENSE
stac_check-1.11.1.dist-info/METADATA
stac_check-1.11.1.dist-info/WHEEL
stac_check-1.11.1.dist-info/entry_points.txt
stac_check-1.11.1.dist-info/top_level.txt
stac_check-1.11.1.dist-info/RECORD
