Metadata-Version: 2.1
Name: stac-check
Version: 1.11.1
Summary: Linting and validation tool for STAC assets
Home-page: https://github.com/stac-utils/stac-check
Author: Jonathan Healy
Author-email: jonathan.d.healy@gmail.com
License: MIT
Requires-Python: >=3.9
License-File: LICENSE
Requires-Dist: requests>=2.32.4
Requires-Dist: jsonschema>=4.25.0
Requires-Dist: click>=8.1.8
Requires-Dist: stac-validator~=3.10.1
Requires-Dist: PyYAML
Requires-Dist: python-dotenv
Provides-Extra: dev
Requires-Dist: pytest; extra == "dev"
Requires-Dist: requests-mock; extra == "dev"
Requires-Dist: types-setuptools; extra == "dev"
Requires-Dist: stac-validator[pydantic]~=3.10.1; extra == "dev"
Provides-Extra: docs
Requires-Dist: sphinx>=8.2.3; extra == "docs"
Requires-Dist: sphinx-click>=6.0.0; extra == "docs"
Requires-Dist: sphinx-rtd-theme>=3.0.2; extra == "docs"
Requires-Dist: myst-parser>=4.0.1; extra == "docs"
Requires-Dist: sphinx-autodoc-typehints>=3.2.0; extra == "docs"
Provides-Extra: pydantic
Requires-Dist: stac-validator[pydantic]~=3.10.1; extra == "pydantic"
